{
    "list": [
        {
            "adminId": "测试内容2o76",
            "compId": "测试内容v756",
            "depOne": "测试内容4it7",
            "depThree": "测试内容iuho",
            "depTwo": "测试内容7my6",
            "empGrade": "测试内容89he",
            "gender": "测试内容c8m0",
            "importTime": "测试内容7m18",
            "jobId": "测试内容e83x",
            "joinDate": "测试内容nd44",
            "phone": "测试内容sr08",
            "signStatus": "测试内容1282",
            "status": "测试内容433w",
            "type": "测试内容ycx8",
            "updateTime": "测试内容64yd",
            "updateUser": "测试内容71ka",
            "userId": 80763,
            "userName": "测试内容l8b8"
        }
    ],
    "total": 85561
}