{
    "list": [
        {
            "backPic": "测试内容483p",
            "certAddress": "测试内容l8hk",
            "confirmFlag": 35633,
            "confirmTime": "测试内容665c",
            "confirmUser": "测试内容o2b6",
            "expireDate": "测试内容pd6d",
            "frontPic": "测试内容j836",
            "ident": "测试内容3bh2",
            "joinDate": "测试内容f25j",
            "status": "测试内容rz74",
            "updateTime": "测试内容eo31",
            "userId": "测试内容74o8",
            "userName": "测试内容7tht"
        }
    ],
    "total": 37213
}